esdt/__init__.py
esdt/pmf.py
esdt/sdt.py
esdt/utils.py
esdt-39.0.dist-info/METADATA
esdt-39.0.dist-info/WHEEL
esdt-39.0.dist-info/namespace_packages.txt
esdt-39.0.dist-info/top_level.txt
esdt-39.0.dist-info/zip-safe
esdt-39.0.dist-info/RECORD
